gitcommit/__init__.py
gitcommit/__main__.py
gitcommit/__version__.py
gitcommit/completers.py
gitcommit/gitcommit.py
gitcommit/style.py
gitcommit/updater.py
gitcommit/utils.py
gitcommit/validators.py
conventional_commit-0.4.2.dist-info/entry_points.txt
conventional_commit-0.4.2.dist-info/LICENSE
conventional_commit-0.4.2.dist-info/WHEEL
conventional_commit-0.4.2.dist-info/METADATA
conventional_commit-0.4.2.dist-info/RECORD
