Metadata-Version: 2.1
Name: conventional-commit
Version: 0.4.2
Summary: a tool for writing conventional commits, conveniently
Home-page: https://github.com/nebbles/gitcommit
Author: nebbles
Requires-Python: >=3.6,<4.0
Classifier: Environment :: Console
Classifier: Intended Audience :: Developers
Classifier: License :: OSI Approved :: GNU General Public License v3 (GPLv3)
Classifier: Natural Language :: English
Classifier: Operating System :: OS Independent
Classifier: Programming Language :: Python :: 3
Classifier: Programming Language :: Python :: 3.6
Classifier: Programming Language :: Python :: 3.7
Classifier: Programming Language :: Python :: 3.8
Classifier: Topic :: Utilities
Requires-Dist: packaging (>=19.2,<20.0)
Requires-Dist: prompt_toolkit (>=3.0,<4.0)
Requires-Dist: pyperclip (>=1.7,<2.0)
Requires-Dist: requests (>=2.22,<3.0)
